setup.py
baoziaction/__init__.py
baoziaction/action.py
baozicore/__init__.py
baozicore/core.py
baozixyz.egg-info/PKG-INFO
baozixyz.egg-info/SOURCES.txt
baozixyz.egg-info/dependency_links.txt
baozixyz.egg-info/top_level.txt