Metadata-Version: 1.0
Name: baozixyz
Version: 0.1.1
Summary: Python automatic operation and maintenance platform
Home-page: UNKNOWN
Author: UNKNOWN
Author-email: UNKNOWN
License: UNKNOWN
Platform: UNKNOWN
